[
  "¬\n0",
  "`\n1",
  "#\n2",
  "~\n3",
  "$\n4",
  "|\n5",
  "£\n6",
  "@\n7",
  "^\n8",
  "%\n9",
  "&\n*",
  ">\n<",
  "]\n[",
  {
    "w": 2
  },
  "Backspace"
],
[
  {
    "w": 1.5
  },
  "Tab",
  "\"\n'",
  "?\n,",
  "!\n.",
  "P",
  "Y",
  "F",
  "G",
  "C",
  "R",
  "L",
  "+\n-",
  "}\n{",
  {
    "x": 0.25,
    "w": 1.25,
    "h": 2,
    "w2": 1.5,
    "h2": 1,
    "x2": -0.25
  },
  "Enter"
],
[
  {
    "w": 1.75
  },
  "Caps Lock",
  "A",
  "O",
  "E",
  "U",
  "I",
  "D",
  "H",
  "T",
  "N",
  "S",
  "_\n=",
  ")\n("
],
[
  {
    "w": 1.25
  },
  "Shift",
  "\\\n/",
  ":\n;",
  "Q",
  "J",
  "K",
  "X",
  "B",
  "M",
  "W",
  "V",
  "Z",
  {
    "w": 2.75
  },
  "Shift"
],
[
  "Fn",
  {
    "w": 1.25
  },
  "Ctrl",
  "Win",
  "Alt",
  {
    "a": 7,
    "w": 5
  },
  "",
  {
    "a": 4,
    "w": 0.9
  },
  "AltGrk",
  {
    "w": 0.9
  },
  "PrtSc",
  {
    "w": 0.9
  },
  "Ctrl"
]
